odoo/addons/partner_grandchildren/README.rst
odoo/addons/partner_grandchildren/__init__.py
odoo/addons/partner_grandchildren/__manifest__.py
odoo/addons/partner_grandchildren/i18n/es.po
odoo/addons/partner_grandchildren/models/__init__.py
odoo/addons/partner_grandchildren/models/res_partner.py
odoo/addons/partner_grandchildren/readme/CONTRIBUTORS.md
odoo/addons/partner_grandchildren/readme/DESCRIPTION.md
odoo/addons/partner_grandchildren/readme/USAGE.md
odoo/addons/partner_grandchildren/static/description/icon.png
odoo/addons/partner_grandchildren/static/description/index.html
odoo/addons/partner_grandchildren/views/res_partner.xml
odoo_addon_partner_grandchildren-17.0.1.0.0.1.dist-info/METADATA
odoo_addon_partner_grandchildren-17.0.1.0.0.1.dist-info/WHEEL
odoo_addon_partner_grandchildren-17.0.1.0.0.1.dist-info/top_level.txt
odoo_addon_partner_grandchildren-17.0.1.0.0.1.dist-info/RECORD
